{
    "mode": "hash",
    "base": "/",
    "routes": [
        {
            "path": "/appshell",
            "name": "appshell",
            "meta": {}
        },
        {
            "path": "/article/checkreal",
            "name": "articleCheckreal",
            "meta": {}
        },
        {
            "path": "/fuli",
            "name": "fuli",
            "meta": {}
        },
        {
            "path": "/fuli-detail",
            "name": "fuliDetail",
            "meta": {}
        },
        {
            "path": "/",
            "name": "index",
            "meta": {}
        },
        {
            "path": "/intro",
            "name": "intro",
            "meta": {}
        },
        {
            "path": "/error",
            "name": "error",
            "meta": {},
            "alias": "*"
        }
    ]
}